Metadata-Version: 1.1
Name: wpversion
Version: 0.1.2
Summary: Script that tries to guess the version of a wordpress installation
Home-page: https://github.com/dealfonso/wpversion
Author: Carlos A.
Author-email: caralla@upv.es
License: MIT
Download-URL: https://github.com/user/reponame/archive/v_011.tar.gz
Keywords: SOME,MEANINGFULL,KEYWORDS
Platform: UNKNOWN
Classifier: Development Status :: 3 - Alpha
Classifier: Intended Audience :: Developers
Classifier: Topic :: Software Development :: Build Tools
Classifier: License :: OSI Approved :: MIT License
Classifier: Programming Language :: Python :: 3
Classifier: Programming Language :: Python :: 3.4
Classifier: Programming Language :: Python :: 3.5
Classifier: Programming Language :: Python :: 3.6
